flytekitplugins/uv/__init__.py
flytekitplugins/uv/image_builder.py
flytekit_uv-0.1.3.dist-info/METADATA
flytekit_uv-0.1.3.dist-info/WHEEL
flytekit_uv-0.1.3.dist-info/entry_points.txt
flytekit_uv-0.1.3.dist-info/licenses/LICENSE
flytekit_uv-0.1.3.dist-info/RECORD
