Metadata-Version: 2.4
Name: flytekit-uv
Version: 0.1.3
Summary: A flytekit plugin for ImageSpec with a UV backend.
Author-email: Francesco Rubbo <francescorubbo@users.noreply.github.com>
License-Expression: MIT
License-File: LICENSE
Classifier: Intended Audience :: Developers
Classifier: Intended Audience :: Science/Research
Classifier: Programming Language :: Python :: 3.12
Classifier: Programming Language :: Python :: 3.13
Classifier: Topic :: Scientific/Engineering
Classifier: Topic :: Scientific/Engineering :: Artificial Intelligence
Classifier: Topic :: Software Development
Classifier: Topic :: Software Development :: Libraries
Classifier: Topic :: Software Development :: Libraries :: Python Modules
Requires-Python: >=3.12
Requires-Dist: flytekit<2,>=1.16
Requires-Dist: pre-commit>=4.2.0
